scseirx/__init__.py
scseirx/agent_SEIRX.py
scseirx/agent_employee.py
scseirx/agent_family_member.py
scseirx/agent_lecturer.py
scseirx/agent_resident.py
scseirx/agent_student.py
scseirx/agent_teacher.py
scseirx/agent_unistudent.py
scseirx/analysis_functions.py
scseirx/construct_school_network.py
scseirx/model_SEIRX.py
scseirx/model_nursing_home.py
scseirx/model_school.py
scseirx/model_uni.py
scseirx/testing_strategy.py
scseirx/viz.py
scseirx/data/nursing_home/interactions_2_quarters.bz2
scseirx/data/nursing_home/interactions_3_quarters.bz2
scseirx/data/nursing_home/interactions_4_quarters.bz2
scseirx/data/nursing_home/interactions_single_quarter.bz2
scseirx/data/school/test_school_primary.bz2
scseirx/img/age_symptom_discount.png
scseirx/img/age_transmission_discount.png
scseirx/img/nursing_home_contact_network_illustration.png
scseirx/img/transmission_risk_progression.png
scseirx-1.4.2.dist-info/LICENSE
scseirx-1.4.2.dist-info/METADATA
scseirx-1.4.2.dist-info/WHEEL
scseirx-1.4.2.dist-info/top_level.txt
scseirx-1.4.2.dist-info/RECORD
