Metadata-Version: 2.1
Name: scseirx
Version: 1.4.2
Summary: A simulation tool to explore the spread of COVID-19 and the impact of prevention measures in small communities such as nursing homes, schools or universities via agent-based modeling (ABM).
Home-page: https://github.com/JanaLasser/agent_based_COVID_SEIRX
Author: Jana Lasser
Author-email: lasser@tugraz.at
License: MIT
Platform: UNKNOWN
Classifier: License :: OSI Approved :: MIT License
Classifier: Programming Language :: Python :: 3
Classifier: Programming Language :: Python :: 3.8
Requires-Dist: numpy (>=1.19.2)
Requires-Dist: scipy (>=1.6.1)
Requires-Dist: matplotlib (==3.3.4)
Requires-Dist: networkx (>=2.5)
Requires-Dist: mesa (>=0.8.8.1)
Requires-Dist: pandas (>=1.2.3)
